setup.py
we_chat/__init__.py
we_chat/mini/__init__.py
we_chat/mini/oauth.py
we_chat/mini/qrcode.py
we_chat/mini/template.py
we_chat/mini/url.py
we_chat/mp/__init__.py
we_chat/mp/oauth.py
we_chat/mp/qrcode.py
we_chat/mp/template.py
we_chat/mp/userinfo.py
we_chat/service/BasicService.py
we_chat/service/BasicSession.py
we_chat/service/__init__.py
we_chat/service/settings.py
we_wechat.egg-info/PKG-INFO
we_wechat.egg-info/SOURCES.txt
we_wechat.egg-info/dependency_links.txt
we_wechat.egg-info/top_level.txt