Metadata-Version: 2.1
Name: we-wechat
Version: 0.0.3
Summary: 微信公众平台及微信商户平台工具包
Home-page: https://github.com/
Author: Zhengkun Chen
Author-email: 1284096697@qq.com
License: UNKNOWN
Platform: UNKNOWN
Classifier: Programming Language :: Python :: 3
Classifier: License :: OSI Approved :: MIT License
Classifier: Operating System :: OS Independent
